{
  "files": [
    {
      "file": "testdata/simple/Dockerfile",
      "violations": [
        {
          "location": {
            "file": "testdata/simple/Dockerfile",
            "start": {
              "line": 3,
              "column": 0
            },
            "end": {
              "line": -1,
              "column": -1
            }
          },
          "rule": "tally/max-lines",
          "message": "file has 3 lines, maximum allowed is 2",
          "severity": "error",
          "docUrl": "https://github.com/tinovyatkin/tally/blob/main/docs/rules/max-lines.md"
        }
      ]
    }
  ],
  "summary": {
    "total": 1,
    "errors": 1,
    "warnings": 0,
    "info": 0,
    "style": 0,
    "files": 1
  }
}

